lab02/mmult.v
`timescale 1ns / 1ps

module mmult(
    input clk,
    input reset_n,
    input enable,
    input [0:9*8-1] A_mat, 
    input [0:9*8-1] B_mat,
    output valid,
    output reg [0:9*17-1] C_mat
    );
    //reg [0:9*17-1]C;
    reg [1:0] c; //counter for how many cycles done, total should be 3
    reg [2:0] j; //counter for the for loop

    always @(reset_n) begin // Triggered when the signal "reset_n" is changed
        if(!reset_n) begin
            C_mat <= 0;
            c <= 0;
        end
    end



    assign valid = (c == 3);
    //Output would not be valid if the calculation is not done or not enabled

    always @(posedge clk) begin
        if(enable) begin
            if(c<3) begin
                for(j=0; j<3; j=j+1) begin
                    C_mat[ (c*3+j)*17 +: 17] <= 
                    A_mat[ (c*3  )*8 +: 8] * B_mat[ (j  )*8 +: 8] + 
                    A_mat[ (c*3+1)*8 +: 8] * B_mat[ (j+3)*8 +: 8] + 
                    A_mat[ (c*3+2)*8 +: 8] * B_mat[ (j+6)*8 +: 8];
                end
                c <= c+1;
            end
        end
        else begin
            c <= 0;
        end
    end
endmodule

lab2/mmult_tb.v
`timescale 1ns / 1ps

module mmult_tb;

// ---------------------------------------------------------------------
// Begin of the simulation code for clock and reset_n signals
//
reg clk = 1;
reg reset_n = 1;

// 100MHz clock generator
always
  #5 clk = !clk;

// Reset signal simulator
event reset_trigger;
initial begin
  forever begin
    @ (reset_trigger);
    @ (negedge clk);
    reset_n = 0;
    @ (negedge clk);
    reset_n = 1;
  end
end
//
//  End of simulation code for clock and reset_n signals
// ---------------------------------------------------------------------

// ---------------------------------------------------------------------
// Begin of the testbench code
//
reg  [0:9*8-1]  A, B;   // 3x3 matrices
wire [0:9*17-1] C;
reg  enable;
wire valid;

reg  [0:9*17-1] result; // The output matrix, 3x3 entries of 17-bit numbers

integer idx;

// Instiantiates a 3x3 matrix multiplier
mmult uut(
  .clk(clk),
  .reset_n(reset_n),
  .enable(enable),
  .A_mat(A),
  .B_mat(B),
  .valid(valid),
  .C_mat(C)
);

initial begin
  $dumpfile("testbench.vcd");
  $dumpvars;
  // Add stimulus here 
  
  // A = 72'h_4F_7E_57_0F_14_7B_21_4C_54;
  // B = 72'h_17_28_3A_40_2F_33_6C_22_77;  
  
  A = 72'h4F7E570F147B214C54;
  B = 72'h17283A402F336C2277;

  // Issue a reset signal
  #10 -> reset_trigger;

  // Wait 100 ns for global reset to finish
  #100 enable = 1;
end

// The matrices multiplication is done. Display the result.
always @(*) begin
  @(posedge valid);

  // Wait one clock cycle so that the output is saved in the result[] register
  #10 $display ("\nMatrix A is:\n");

  for (idx = 0; idx < 9; idx = idx+1) begin
    $write (" %d ", A[idx*8 +: 8]);
    if (idx%3 == 2) $write("\n");
  end

  #10 $display ("\nMatrix B is:\n");

  for (idx = 0; idx < 9; idx = idx+1)
  begin
    $write (" %d ", B[idx*8 +: 8]);
    if (idx%3 == 2) $write("\n");
  end

  $display ("\nThe result of C = A x B is:\n");

  for (idx = 0; idx < 9; idx = idx+1)
  begin
    $write (" %d ", result[idx*17 +: 17]);
    if (idx%3 == 2) $write("\n");
  end

  $write("\n");
end

// Save output C matrix in the result register when (valid == 1)
always @(posedge clk) begin
  if (~reset_n)
    result <= 0;
  else if (valid)
    result <= C;
  else
    result <= result;
end
//
//  End of the testbench code
// ---------------------------------------------------------------------

endmodule

lab02/testbench.vcd
$date
	Mon Oct  3 11:22:00 2022
$end
$version
	Icarus Verilog
$end
$timescale
	1ps
$end
$scope module mmult_tb $end
$var event 1 ! reset_trigger $end
$var wire 1 " valid $end
$var wire 153 # C [0:152] $end
$var reg 72 $ A [0:71] $end
$var reg 72 % B [0:71] $end
$var reg 1 & clk $end
$var reg 1 ' enable $end
$var reg 1 ( reset_n $end
$var reg 153 ) result [0:152] $end
$var integer 32 * idx [31:0] $end
$scope module uut $end
$var wire 72 + A_mat [0:71] $end
$var wire 72 , B_mat [0:71] $end
$var wire 1 & clk $end
$var wire 1 ' enable $end
$var wire 1 ( reset_n $end
$var wire 1 " valid $end
$var reg 153 - C_mat [0:152] $end
$var reg 2 . c [1:0] $end
$var reg 3 / j [2:0] $end
$upscope $end
$upscope $end
$enddefinitions $end
#0
$dumpvars
bx /
b0 .
bx -
b101110010100000111010010000000010111100110011011011000010001001110111 ,
b10011110111111001010111000011110001010001111011001000010100110001010100 +
bx *
bx )
1(
x'
1&
b101110010100000111010010000000010111100110011011011000010001001110111 %
b10011110111111001010111000011110001010001111011001000010100110001010100 $
bx #
0"
1!
$end
#5000
0&
#10000
1&
1!
#15000
b0 #
b0 -
0(
0&
#20000
b0 )
1&
#25000
1(
0&
#30000
1&
#35000
0&
#40000
1&
#45000
0&
#50000
1&
#55000
0&
#60000
1&
#65000
0&
#70000
1&
#75000
0&
#80000
1&
#85000
0&
#90000
1&
#95000
0&
#100000
1&
#105000
0&
#110000
b1 .
b1001011010011010001011110000100000101001101110001000000000000000000000000000000000000000000000000000000000000000000000000000000000000000000000000000000 #
b1001011010011010001011110000100000101001101110001000000000000000000000000000000000000000000000000000000000000000000000000000000000000000000000000000000 -
b11 /
1&
1'
#115000
0&
#120000
b10 .
b1001011010011010001011110000100000101001101110001000111010001111010000101100101101000100000010001111000000000000000000000000000000000000000000000000000 #
b1001011010011010001011110000100000101001101110001000111010001111010000101100101101000100000010001111000000000000000000000000000000000000000000000000000 -
b11 /
1&
#125000
0&
#130000
1"
b11 .
b1001011010011010001011110000100000101001101110001000111010001111010000101100101101000100000010001111000111001011001110000111100100010000011110110101010 #
b1001011010011010001011110000100000101001101110001000111010001111010000101100101101000100000010001111000111001011001110000111100100010000011110110101010 -
b11 /
1&
#135000
0&
#140000
b1001011010011010001011110000100000101001101110001000111010001111010000101100101101000100000010001111000111001011001110000111100100010000011110110101010 )
1&
b1001 *
#145000
0&
#150000
1&
b1001 *
