lab3/alu.v
`timescale 1ns / 1ps

module alu (
    output reg [7:0] alu_out, 
    output wire zero, 
    input[2:0] opcode, 
    input signed [7:0] accum, 
    input signed [7:0] data, 
    input reset,
    input clk);

    reg [7:0] temp;
    assign zero = !(|(0^accum));
    reg signed [3:0] a;
    reg signed [3:0] b;
 
    always @ (posedge clk) begin
        if(!reset) begin
            a[3:0] <= accum[3:0];
            b[3:0] <= data[3:0];
            if(opcode == 3'bxxx) 
                alu_out = 0; 
            else begin
                case(opcode)
                    0: alu_out <= accum; 
                    1: alu_out <= accum + data;
                    2: alu_out <= accum - data;
                    3: alu_out <= accum & data;
                    4: alu_out <= accum ^ data;
                    5: alu_out <= accum[7] ? ~accum+1 : accum;
                    6: alu_out <= a*b;
                    // 6: alu_out <= (accum[3]^data[3]) ? 
                    //                 ((accum[3]) ? 
                    //                     -((-accum[2:0]&8'h07)*data[2:0]): 
                    //                     -((-data[2:0]&8'h07)*accum[2:0])):
                    //                 (accum[2:0]*data[2:0]);
                    7: alu_out <= data;
                    default: alu_out <= 0;
                endcase
            end
        end
        else begin
            alu_out <= 0;
        end
    end
endmodule

lab03/alu_demo_tb.v
/*********************************************************************
 * Stimulus for the ALU design - Verilog Training Course
 *********************************************************************/
`timescale 1ns / 1ns
module alu_demo_tb;
  wire [7:0] alu_out;
  reg  [7:0] data, accum;
  reg  [2:0] opcode;
  integer    i, err_cnt, k;
  wire [7:0] twocomp_accum;
  wire [7:0] abs_accum;
  
  wire [3:0] accum_4b;
  wire [3:0] data_4b;
  wire [3:0] abs_accum_4b;
  wire [3:0] abs_data_4b;
  wire [7:0] umul;
  wire [7:0] mul;
  wire [7:0] mask;
  
  reg clk, reset;
  
  parameter ranseed = 9'h1ff;
  
// Instantiate the ALU.  Named mapping allows the designer to have freedom
//    with the order of port declarations

  alu   alu1 (.alu_out(alu_out), .zero(zero),               //outputs from ALU
	      .opcode(opcode), .data(data & mask), .accum(accum & mask), .clk(clk), .reset(reset)); //inputs to ALU

  //define mnemonics to represent opcodes
  `define PASSA 3'b000
  `define ADD   3'b001
  `define SUB   3'b010
  `define AND   3'b011
  `define XOR   3'b100
  `define ABS   3'b101
  `define MUL   3'b110
  `define PASSD 3'b111

// Define a safe delay between each strobing of the ALU inputs/outputs
  `define strobe      20
  `define testnumber  3
  assign  twocomp_accum = ~accum + 8'b1;

  assign  abs_accum = (accum[7])? twocomp_accum : accum;

  assign accum_4b = accum[3:0];
  assign data_4b = data[3:0];

  assign abs_accum_4b = (accum_4b[3])?~accum_4b + 4'b1:accum_4b;
  assign abs_data_4b = (data_4b[3])?~data_4b + 4'b1:data_4b;

  assign umul = abs_accum_4b * abs_data_4b;
  assign mul = (accum_4b[3]^data_4b[3])?~umul+8'b1:umul;

  assign mask = (opcode == 3'b110)? 8'h0f: 8'hff;

  // clock generate
  initial   clk = 0;
  always #(`strobe/2) clk = ~clk;

  // pattern generate
  initial
  begin
    $dumpfile("testbench.vcd");
    $dumpvars;
    
    // SET UP THE OUTPUT FORMAT FOR THE TEXT DISPLAY
    $display("\t\t\t\t\t\t            INPUTS                  EXPECTD OUTPUTS        REAL    OUTPUT  \n");
    $display("\t\t\t\t\t\t  OPCODE   DATA IN    ACCUM IN  |  ALU OUT   ZERO BIT |  ALU OUT   ZERO BIT");
    $display("\t\t\t\t\t\t  ------   --------   --------  |  --------  -------- |  --------  --------");
    $timeformat(-9, 1, " ns", 9); //Display time in nanoseconds
    err_cnt = 0;   
    reset = 0;
    
    # `strobe;
    accum = 8'h37;
    data = 8'hD6;
    reset = 1;
    # `strobe;
    $display ("initial test, reset enable, alu_out = %b", alu_out);
    if (alu_out != 8'h00) begin 
      err_cnt = err_cnt + 1;
      $display ("ERROR: After reset ALU, alu_out should be zero.");
    end
    # `strobe;
      reset = 0;
    for (k = 0; k < `testnumber; k = k + 1)
    begin      
      for (i = 0; i < 8; i = i + 1)  //VERIFY OPERATION FOR ALL 8 OPCODES
      begin
        @(negedge clk)
        //change inputs at strobe point
        #(`strobe/4) opcode = i;
        // APPLY STIMULUS TO THE INPUT PINS
        accum = $random % ranseed;                //Initialize inputs to the ALU
        data = $random % ranseed;
        //Wait for ALU to process inputs
        #(`strobe*3/2)   check_outputs; //call a task to verify outputs
      end
    end

    //VERIFY OPERATION WITH UNKNOWN OPCODE
    @(negedge clk)  #(`strobe/4)  opcode = 3'b0x0;
    #(`strobe*3/2)   check_outputs;

    @(negedge clk)  #(`strobe/4)  opcode = 3'bx0x;
    #(`strobe*3/2)   check_outputs;

    //VERIFY OPERATION OF ZERO BIT
    @(negedge clk) #(`strobe/4) accum = 8'h00; opcode = `ADD;
    #(`strobe*3/2)   check_outputs;
      
    //VERIFY OPERATION OF SIGNED MULTIPLICATION
    @(negedge clk) #(`strobe/4) accum = 8'hff; data = 8'hff; opcode = `MUL; //Output should be 8'h01
    #(`strobe*3/2)   check_outputs;
      
    @(negedge clk) #(`strobe/4) accum = 8'h0f; data = 8'hf1; opcode = `MUL; //Output should be 8'hff
    #(`strobe*3/2)   check_outputs;

    //WAIT 1 MORE STROBE AND THEN FINISH
    #`strobe 
    if (err_cnt) $display("\nThere were %d errors in all.\n", err_cnt);
    else $display("\nNo errors were found!\n");
    #`strobe
    $display("Got %d / 90 in this part.\n", (30-err_cnt)*3);
    #10000 $finish;
  end

/**********************************************************************
 * SUBROUTINES TO COMPARE THE ALU OUTPUTS TO EXPECTED RESULTS
 *********************************************************************/
  task check_outputs;
    casez (opcode)
      `PASSA  : begin
                $display("PASS ACCUM OPERATION:",
                          "      %b     %b   %b  |  %b      %b    |  %b      %b",
                          opcode, data, accum, accum, !accum, alu_out, zero);
                if ((alu_out !== accum) || (zero !== !accum)) error;
                end
      `ADD    : begin
                  $display("ADD OPERATION       :",
                          "      %b     %b   %b  |  %b      %b    |  %b      %b",
                          opcode, data, accum, (accum+data), !accum, alu_out, zero);
                  if ((alu_out !== (accum + data)) || (zero !== !accum)) error;
                end
      `SUB    : begin
                  $display("SUB OPERATION       :",
                          "      %b     %b   %b  |  %b      %b    |  %b      %b",
                          opcode, data, accum, (accum-data), !accum, alu_out, zero);
                  if ((alu_out !== (accum - data)) || (zero !== !accum)) error;
                end
      `AND    : begin
                  $display("AND OPERATION       :",
                          "      %b     %b   %b  |  %b      %b    |  %b      %b",
                          opcode, data, accum, (accum&data), !accum, alu_out, zero);
                  if ((alu_out !== (accum & data)) || (zero !== !accum)) error;
                end
      `XOR   : begin
                  $display("XOR OPERATION       :",
                          "      %b     %b   %b  |  %b      %b    |  %b      %b",
                          opcode, data, accum, (accum^data), !accum, alu_out, zero);
                  if ((alu_out !== (accum ^ data)) || (zero !== !accum)) error;
                end
      `ABS    : begin
                  $display("ABS OPERATION       :",
                          "      %b     %b   %b  |  %b      %b    |  %b      %b",
                          opcode, data, accum, abs_accum, !accum, alu_out, zero);
                  if ((alu_out !== abs_accum) || (zero !== !accum)) error;
                end
      `MUL    : begin
                  $display("MUL OPERATION       :",
                          "      %b     %b   %b  |  %b      %b    |  %b      %b",
                          opcode, data & mask, accum & mask, mul, !accum, alu_out, zero);
                  if ((alu_out !== mul) || (zero !== !(accum & mask))) error;
                end
      `PASSD  : begin
                  $display("PASS DATA OPERATION :",
                          "      %b     %b   %b  |  %b      %b    |  %b      %b",
                          opcode, data, accum, data, !accum, alu_out, zero);
                  if ((alu_out !== data) || (zero !== !accum)) error;
                end
      default : begin
                  $display("UNKNOWN OPERATION   :",
                          "      %b     %b   %b  |  %b      %b    |  %b      %b",
                          opcode, data, accum, 8'b0, !accum,alu_out, zero);
                  if ((alu_out !== 8'b0) || (zero !== !accum)) error;
                end
    endcase
  endtask

  task error;
    begin
      $display("\t\t\t ERROR AT %t,  ERROR OUTPUT : ALU_OUT = %b, ZERO_BIT = %b\n",
               $realtime, alu_out, zero);
      err_cnt = err_cnt + 1;
    end
  endtask

endmodule

lab3/testbench.vcd
$date
	Mon Oct 17 19:42:22 2022
$end
$version
	Icarus Verilog
$end
$timescale
	1ps
$end
$scope module alu_demo_tb $end
$var wire 1 ! zero $end
$var wire 8 " umul [7:0] $end
$var wire 8 # twocomp_accum [7:0] $end
$var wire 8 $ mul [7:0] $end
$var wire 8 % mask [7:0] $end
$var wire 4 & data_4b [3:0] $end
$var wire 8 ' alu_out [7:0] $end
$var wire 4 ( accum_4b [3:0] $end
$var wire 4 ) abs_data_4b [3:0] $end
$var wire 4 * abs_accum_4b [3:0] $end
$var wire 8 + abs_accum [7:0] $end
$var reg 8 , accum [7:0] $end
$var reg 1 - clk $end
$var reg 8 . data [7:0] $end
$var reg 3 / opcode [2:0] $end
$var reg 1 0 reset $end
$var integer 32 1 err_cnt [31:0] $end
$var integer 32 2 i [31:0] $end
$var integer 32 3 k [31:0] $end
$scope module alu1 $end
$var wire 8 4 accum [7:0] $end
$var wire 1 - clk $end
$var wire 8 5 data [7:0] $end
$var wire 3 6 opcode [2:0] $end
$var wire 1 0 reset $end
$var wire 1 ! zero $end
$var reg 4 7 a [3:0] $end
$var reg 8 8 alu_out [7:0] $end
$var reg 4 9 b [3:0] $end
$upscope $end
$scope task check_outputs $end
$upscope $end
$scope task error $end
$upscope $end
$upscope $end
$enddefinitions $end
#0
$dumpvars
bx 9
bx 8
bx 7
bx 6
bx 5
bx 4
bx 3
bx 2
b0 1
00
bx /
bx .
0-
bx ,
bx +
bx *
bx )
bx (
bx '
bx &
bx1111 %
bx $
bx #
bx "
x!
$end
#10000
b0 '
b0 8
1-
#20000
b101010 $
b101010 "
b110 )
b111 *
0!
b110 &
bx0x0110 5
b110111 +
b111 (
b11001001 #
b0xx0111 4
0-
10
b11010110 .
b110111 ,
#30000
1-
#40000
0-
#50000
1-
#60000
0-
b0 2
b0 3
00
#65000
b11011100 $
b110 )
b100100 "
b110 *
b1010 &
b1101010 5
b1000110 +
b110 (
b10111010 #
b1000110 4
b11111111 %
b1101010 .
b1000110 ,
b0 /
b0 6
#70000
b1000110 '
b1000110 8
b1010 9
b110 7
1-
#80000
0-
#90000
1-
#95000
b1 2
#100000
0-
#105000
b0 $
b0 )
b0 "
b101 *
b0 &
b100000 5
b1011011 +
b101 (
b1011011 #
b10100101 4
b100000 .
b10100101 ,
b1 /
b1 6
#110000
b11000101 '
b11000101 8
b0 9
b101 7
1-
#120000
0-
#130000
1-
#135000
b10 2
#140000
0-
#145000
b101010 $
b101010 "
b110 )
b111 *
b1111001 +
b1010 &
b11010 5
b1001 (
b10000111 #
b1111001 4
b11010 .
b1111001 ,
b10 /
b10 6
#150000
b1011111 '
b1011111 8
b1010 9
b1001 7
1-
#160000
0-
#170000
1-
#175000
b11 2
#180000
0-
#185000
b1100 $
b1100 "
b10 *
b1101110 +
b1110 (
b10010010 #
b1101110 4
b1101110 ,
b11 /
b11 6
#190000
b1010 '
b1010 8
b1110 7
1-
#200000
0-
#210000
1-
#215000
b100 2
#220000
0-
#225000
b110 $
b110 "
b1 *
b10101010 5
b101111 +
b1111 (
b11010001 #
b101111 4
b10101010 .
b101111 ,
b100 /
b100 6
#230000
b10000101 '
b10000101 8
b1111 7
1-
#240000
0-
#250000
1-
#255000
b101 2
#260000
0-
#265000
b11001010 5
b111111 +
b11000001 #
b111111 4
b11001010 .
b111111 ,
b101 /
b101 6
#270000
b111111 '
b111111 8
1-
#280000
0-
#290000
1-
#295000
b110 2
#300000
0-
#305000
b10000 $
b100 )
b10000 "
b100 *
b1100 &
b1100 5
b100100 +
b1100 (
b100100 #
b1100 4
b1111 %
b11100 .
b11011100 ,
b110 /
b110 6
#310000
b110 '
b110 8
b1100 9
b1100 7
1-
#320000
0-
#330000
b10000 '
b10000 8
1-
#335000
b111 2
#340000
0-
#345000
b11111010 $
b10 )
b110 "
b11 *
b111101 +
b10 &
b1000010 5
b1101 (
b11000011 #
b111101 4
b11111111 %
b1000010 .
b111101 ,
b111 /
b111 6
#350000
b1000010 '
b1000010 8
b10 9
b1101 7
1-
#360000
0-
#370000
1-
#375000
b1 3
b0 2
#380000
0-
#385000
b10 $
b10 "
b1 *
b11110010 5
b1100001 +
b1 (
b10011111 #
b1100001 4
b11110010 .
b1100001 ,
b0 /
b0 6
#390000
b1100001 '
b1100001 8
b1 7
1-
#400000
0-
#410000
1-
#415000
b1 2
#420000
0-
#425000
b10100 $
b100 )
b10100 "
b101 *
b1100 &
b10111100 5
b1100101 +
b1011 (
b1100101 #
b10011011 4
b10111100 .
b10011011 ,
b1 /
b1 6
#430000
b1010111 '
b1010111 8
b1100 9
b1011 7
1-
#440000
0-
#450000
1-
#455000
b10 2
#460000
0-
#465000
b11111010 $
b1 )
b110 "
b110 *
b100110 +
b1 &
b1 5
b1010 (
b100110 #
b11011010 4
b1 .
b11011010 ,
b10 /
b10 6
#470000
b11011001 '
b11011001 8
b1 9
b1010 7
1-
#480000
0-
#490000
1-
#495000
b11 2
#500000
0-
#505000
b1000 $
b10 *
b1000 "
b100 )
b1111110 +
b100 &
b10100 5
b10 (
b1111110 #
b10000010 4
b10100 .
b10000010 ,
b11 /
b11 6
#510000
b0 '
b0 8
b100 9
b10 7
1-
#520000
0-
#530000
1-
#535000
b100 2
#540000
0-
#545000
b11101100 $
b101 )
b10100 "
b100 *
b1000100 +
b1011 &
b10111011 5
b100 (
b10111100 #
b1000100 4
b10111011 .
b1000100 ,
b100 /
b100 6
#550000
b11111111 '
b11111111 8
b1011 9
b100 7
1-
#560000
0-
#570000
1-
#575000
b101 2
#580000
0-
#585000
b0 $
b0 )
b0 "
b100 *
b0 &
b10010000 5
b11100 +
b1100 (
b11100100 #
b11100 4
b10010000 .
b11100 ,
b101 /
b101 6
#590000
b11100 '
b11100 8
b0 9
b1100 7
1-
#600000
0-
#610000
1-
#615000
b110 2
#620000
0-
#625000
b11010000 $
b110 *
b110000 "
b1000 )
b1000 &
b1000 5
b1101010 +
b110 (
b1101010 #
b110 4
b1111 %
b10111000 .
b10010110 ,
b110 /
b110 6
#630000
b0 '
b0 8
b1000 9
b110 7
1-
#640000
0-
#650000
b11010000 '
b11010000 8
1-
#655000
b111 2
#660000
0-
#665000
b11100010 $
b11110 "
b101 )
b1011010 +
b1011 &
b101011 5
b1011010 #
b10100110 4
b11111111 %
b101011 .
b10100110 ,
b111 /
b111 6
#670000
b101011 '
b101011 8
b1011 9
1-
#680000
0-
#690000
1-
#695000
b10 3
b0 2
#700000
0-
#705000
b101000 $
b101000 "
b1000 *
b111000 +
b1001011 5
b1000 (
b11001000 #
b111000 4
b1001011 .
b111000 ,
b0 /
b0 6
#710000
b111000 '
b111000 8
b1000 7
1-
#720000
0-
#730000
1-
#735000
b1 2
#740000
0-
#745000
b0 $
b0 )
b0 "
b101 *
b0 &
b11010000 5
b110101 +
b101 (
b11001011 #
b110101 4
b11010000 .
b110101 ,
b1 /
b1 6
#750000
b101 '
b101 8
b0 9
b101 7
1-
#760000
0-
#770000
1-
#775000
b10 2
#780000
0-
#785000
b110 $
b110 "
b1 )
b110 *
b1 &
b1100001 5
b1101010 +
b110 (
b1101010 #
b10010110 4
b1100001 .
b10010110 ,
b10 /
b10 6
#790000
b110101 '
b110101 8
b1 9
b110 7
1-
#800000
0-
#810000
1-
#815000
b11 2
#820000
0-
#825000
b11000 $
b11 )
b11000 "
b1000 *
b11000 +
b1101 &
b10111101 5
b1000 (
b11000 #
b11101000 4
b10111101 .
b11101000 ,
b11 /
b11 6
#830000
b10101000 '
b10101000 8
b1101 9
b1000 7
1-
#840000
0-
#850000
1-
#855000
b100 2
#860000
0-
#865000
b11111000 $
b1000 "
b1 )
b111000 +
b1 &
b10110001 5
b111000 #
b11001000 4
b10110001 .
b11001000 ,
b100 /
b100 6
#870000
b1111001 '
b1111001 8
b1 9
1-
#880000
0-
#890000
1-
#895000
b101 2
#900000
0-
#905000
b1100 $
b100 *
b1100 "
b11 )
b100 +
b1101 &
b10111101 5
b1100 (
b100 #
b11111100 4
b10111101 .
b11111100 ,
b101 /
b101 6
#910000
b100 '
b100 8
b1101 9
b1100 7
1-
#920000
0-
#930000
1-
#935000
b110 2
#940000
0-
#945000
b10010 $
b110 )
b10010 "
b11 *
b101101 +
b110 &
b110 5
b11 (
b101101 #
b11 4
b1111 %
b10010110 .
b11010011 ,
b110 /
b110 6
#950000
b1100 '
b1100 8
b110 9
b11 7
1-
#960000
0-
#970000
b10010 '
b10010 8
1-
#975000
b111 2
#980000
0-
#985000
b110 $
b1 )
b110 "
b110 *
b1010110 +
b1111 &
b11111111 5
b1010 (
b1010110 #
b10101010 4
b11111111 %
b11111111 .
b10101010 ,
b111 /
b111 6
#990000
b11111111 '
b11111111 8
b1111 9
b1010 7
1-
#1000000
0-
#1010000
1-
#1015000
b11 3
b1000 2
#1020000
0-
#1025000
b0x0 /
b0x0 6
#1030000
b0 '
b0 8
1-
#1040000
0-
#1050000
1-
#1060000
0-
#1065000
bx0x /
bx0x 6
#1070000
1-
#1080000
0-
#1090000
1-
#1100000
0-
#1105000
b0 $
b0 "
b0 *
b0 +
1!
b0 (
b0 #
b0 4
b1 /
b1 6
b0 ,
#1110000
b11111111 '
b11111111 8
b0 7
1-
#1120000
0-
#1130000
1-
#1140000
0-
#1145000
b1 $
b1111 5
b1 "
b1 *
0!
b1111 %
b1 +
b1111 (
b1 #
b1111 4
b110 /
b110 6
b11111111 ,
#1150000
b0 '
b0 8
b1111 7
1-
#1160000
0-
#1170000
b1 '
b1 8
1-
#1180000
0-
#1185000
b11111111 $
b1111 +
b1 &
b1 5
b11110001 #
b11110001 .
b1111 ,
#1190000
b1 9
1-
#1200000
0-
#1210000
b11111111 '
b11111111 8
1-
